bk7084-0.3.16.dist-info/METADATA
bk7084-0.3.16.dist-info/WHEEL
bk7084-0.3.16.dist-info/licenses/LICENSE
bk7084/bk7084.pyi
bk7084/__init__.py
bk7084/mesh.py
bk7084/math/matrix.py
bk7084/math/vector.py
bk7084/math/quaternion.py
bk7084/math/__init__.py
bk7084/math/bbox.py
bk7084/camera.py
bk7084/input.py
bk7084/geometry.py
bk7084/app.py
bk7084/py.typed
bk7084/bkfw.cpython-39-darwin.so
bk7084-0.3.16.dist-info/RECORD
